aws_ir/__init__.py
aws_ir/_version.py
aws_ir/cli.py
aws_ir/libs/__init__.py
aws_ir/libs/aws.py
aws_ir/libs/case.py
aws_ir/libs/compromised.py
aws_ir/libs/connection.py
aws_ir/libs/inventory.py
aws_ir/libs/plugin.py
aws_ir/libs/s3bucket.py
aws_ir/libs/volatile.py
aws_ir/plans/__init__.py
aws_ir/plans/host.py
aws_ir/plans/key.py
aws_ir-0.3.3.data/scripts/aws_ir
aws_ir-0.3.3.dist-info/METADATA
aws_ir-0.3.3.dist-info/RECORD
aws_ir-0.3.3.dist-info/WHEEL
aws_ir-0.3.3.dist-info/top_level.txt
aws_ir-0.3.3.dist-info/zip-safe
