Metadata-Version: 2.1
Name: aws-ir
Version: 0.3.3
Summary: AWS Incident Response ToolKit
Home-page: https://github.com/ThreatResponse/aws_ir
Author: Andrew Krug, Alex McCormack, Joel Ferrier, Jeff Parr
Author-email: andrewkrug@gmail.com,developer@amccormack.net,joel@ferrier.io
License: MIT
Download-URL: https://github.com/ThreatResponse/aws_ir/archive/v0.3.0.tar.gz
Platform: UNKNOWN
Requires-Dist: boto3 (>=1.3.0)
Requires-Dist: progressbar-latest
Requires-Dist: logutils (==0.3.3)
Requires-Dist: requests
Requires-Dist: structlog
Requires-Dist: pytz
Requires-Dist: jinja2
Requires-Dist: pluginbase
Requires-Dist: margaritashotgun (>=0.4.1)
Requires-Dist: aws-ir-plugins (>=0.0.3)
